seaplane/common/__init__.py
seaplane/common/spinner.py
seaplane/common/sse.py
seaplane.common-0.0.2.dist-info/LICENSE
seaplane.common-0.0.2.dist-info/METADATA
seaplane.common-0.0.2.dist-info/WHEEL
seaplane.common-0.0.2.dist-info/top_level.txt
seaplane.common-0.0.2.dist-info/RECORD
